zxynewpkgcheckupstream/__init__.py
zxynewpkgcheckupstream/print_hi.py
zxynewpkgcheckupstream-0.0.3.dist-info/LICENSE
zxynewpkgcheckupstream-0.0.3.dist-info/METADATA
zxynewpkgcheckupstream-0.0.3.dist-info/WHEEL
zxynewpkgcheckupstream-0.0.3.dist-info/top_level.txt
zxynewpkgcheckupstream-0.0.3.dist-info/RECORD
