Metadata-Version: 2.1
Name: zxynewpkgcheckupstream
Version: 0.0.3
Summary: A small package
Home-page: https://github.com/gituser/example-pkg
Author: zxynewpkgcheckupstream
Author-email: zxynewpkgcheckupstream@zxynewpkgcheckupstream.com
License: GPT
Platform: UNKNOWN
Requires-Python: >=3.6
Requires-Dist: Django (>=2.0)
